esentity/__init__.py
esentity/api.py
esentity/encoder.py
esentity/ext.py
esentity/filters.py
esentity/models.py
esentity/routes.py
esentity/tasks.py
esentity/telegram.py
esentity-0.2.277.dist-info/WHEEL
esentity-0.2.277.dist-info/METADATA
esentity-0.2.277.dist-info/RECORD
