Metadata-Version: 2.1
Name: esentity
Version: 0.2.277
Summary: Elasticsearch Entity Tools
Home-page: https://slotmarks.com
Author: Slotmarks
Author-email: info@slotmarks.com
Requires-Python: >=3.7,<4.0
Classifier: Programming Language :: Python :: 3
Classifier: Programming Language :: Python :: 3.7
Classifier: Programming Language :: Python :: 3.8
Classifier: Programming Language :: Python :: 3.9
